README.md
setup.py
weatherbroker/__init__.py
weatherbroker/engine.py
weatherbroker.egg-info/PKG-INFO
weatherbroker.egg-info/SOURCES.txt
weatherbroker.egg-info/dependency_links.txt
weatherbroker.egg-info/requires.txt
weatherbroker.egg-info/top_level.txt
weatherbroker/providers/__init__.py
weatherbroker/providers/darksky.py
weatherbroker/providers/openweathermap.py
weatherbroker/providers/weatherbit.py