Metadata-Version: 2.1
Name: weatherbroker
Version: 0.0.2
Summary: Weather broker for Python
Home-page: https://github.com/alttch/weatherbroker
Author: Altertech Group
Author-email: pr@altertech.com
License: Apache License 2.0
Platform: UNKNOWN
Classifier: Programming Language :: Python :: 3
Classifier: License :: OSI Approved :: Apache Software License
Classifier: Topic :: Scientific/Engineering :: Atmospheric Science
